cqd/__init__.py
cqd/open_xpd_uuid/__init__.py
cqd/open_xpd_uuid/__version__.py
cqd/py.typed
open_xpd_uuid-1.1.0.dist-info/LICENSE
open_xpd_uuid-1.1.0.dist-info/METADATA
open_xpd_uuid-1.1.0.dist-info/WHEEL
open_xpd_uuid-1.1.0.dist-info/RECORD
