Metadata-Version: 2.3
Name: open-xpd-uuid
Version: 1.1.0
Summary: A library for creating and managing globally-unique open-xpd-uuid namespaces for product declarations.
License: Apache-2.0
Author: C-Change Labs
Author-email: support@c-change-labs.com
Maintainer: C-Change Labs
Maintainer-email: open-source@c-change-labs.com
Requires-Python: >=3.9,<4.0
Classifier: Operating System :: OS Independent
Classifier: Topic :: Software Development :: Libraries :: Python Modules
Classifier: Development Status :: 5 - Production/Stable
Classifier: Intended Audience :: Developers
Classifier: License :: OSI Approved :: Apache Software License
Classifier: Programming Language :: Python
Classifier: Programming Language :: Python :: 3.9
Classifier: Programming Language :: Python :: 3.10
Classifier: Programming Language :: Python :: 3.11
Classifier: Programming Language :: Python :: 3.12
Classifier: Programming Language :: Python :: 3.13
Classifier: Programming Language :: Python :: 3.14
